.gitignore
.gitlab-ci.yml
LICENSE.txt
README.md
ci_build_deb.sh
pyproject.toml
setup.py
.github/workflows/release.yml
austaltools/TODO.md
austaltools/__init__.py
austaltools/_corine.py
austaltools/_datasets.py
austaltools/_dispersion.py
austaltools/_fetch_dwd_obs.py
austaltools/_geo.py
austaltools/_metadata.py
austaltools/_netcdf.py
austaltools/_plotting.py
austaltools/_storage.py
austaltools/_tools.py
austaltools/_version.py
austaltools/_windutil.py
austaltools/_wmo_metadata.py
austaltools/austal_input.py
austaltools/command_line.py
austaltools/configure_austaltools.py
austaltools/eap.py
austaltools/fill_timeseries.py
austaltools/heating.py
austaltools/import_buildings.py
austaltools/input_terrain.py
austaltools/input_weather.py
austaltools/plot.py
austaltools/simple.py
austaltools/steepness.py
austaltools/transform.py
austaltools/windfield.py
austaltools/windrose.py
austaltools.egg-info/PKG-INFO
austaltools.egg-info/SOURCES.txt
austaltools.egg-info/dependency_links.txt
austaltools.egg-info/entry_points.txt
austaltools.egg-info/not-zip-safe
austaltools.egg-info/requires.txt
austaltools.egg-info/top_level.txt
austaltools/_mock/__init__.py
austaltools/_mock/netCDF4.py
austaltools/data/DGM10-HE.LICENSE.txt
austaltools/data/GLO-30.LICENSE.txt
austaltools/data/__init__.py
austaltools/data/dataset_definitions.json
austaltools/data/dwd_stationlist.json
austaltools/data/scrape_places_names_HE.py
austaltools/data/scrape_wmo_stationlist.py
austaltools/data/wmo_stationlist.json
docs/api_commands.rst
docs/api_internal.rst
docs/austaltools.rst
docs/conf.py
docs/configure-austaltools.rst
docs/fill-timeseries.rst
docs/heating.rst
docs/index.rst
docs/install.rst
docs/references.rst
docs/img/plot_contour_2sigma.png
docs/img/plot_window.png
heating/partition_distance.py
heating/plot_flux_wall_all_month_2003-07.py
heating/plot_temp_room_room_month_2003-04.py
heating/plot_temp_room_room_month_2003-07.py
heating/plot_temp_wall_back_day_2003-04-01.py
heating/plot_temp_wall_back_heatup_2003-01-01.py
heating/plot_temp_wall_back_month_2003-04.py
tests/__init__.py
tests/example.akterm
tests/test.dmna
tests/test__corine.py
tests/test__datasets.py
tests/test__dispersion.py
tests/test__fetch_dwd_obs.py
tests/test__geo.py
