Metadata-Version: 2.4
Name: austaltools
Version: 2.8.26
Summary: Tools for use with the Lagrangian atmospheric pollutant dispersion model AUSTAL (AUSbreitungsmodell nach TA-Luft).
Author-email: Clemens Drüe <druee@uni-trier.de>
License: EUPL-1.2
Project-URL: Homepage, https://github.com/cdruee/austaltools
Project-URL: Repository, https://github.com/cdruee/austaltools
Project-URL: Issues, https://github.com/cdruee/austaltools/issues
Project-URL: Documentation, https://austaltools.readthedocs.io
Keywords: meteorology,air quality,modeling
Classifier: Development Status :: 4 - Beta
Classifier: Intended Audience :: Science/Research
Classifier: Programming Language :: Python :: 3
Classifier: Programming Language :: Python :: 3.8
Classifier: Programming Language :: Python :: 3.9
Classifier: Programming Language :: Python :: 3.10
Classifier: Programming Language :: Python :: 3.11
Classifier: Programming Language :: Python :: 3.12
Requires-Python: >=3.8
License-File: LICENSE.txt
Requires-Dist: cdsapi
Requires-Dist: gdal
Requires-Dist: matplotlib
Requires-Dist: meteolib
Requires-Dist: netcdf4
Requires-Dist: numpy
Requires-Dist: pandas
Requires-Dist: pyyaml
Requires-Dist: readmet
Requires-Dist: requests
Requires-Dist: setuptools
Requires-Dist: tqdm
Requires-Dist: urllib3
Provides-Extra: docs
Requires-Dist: sphinx; extra == "docs"
Requires-Dist: sphinx-argparse; extra == "docs"
Provides-Extra: test
Requires-Dist: pytest; extra == "test"
Requires-Dist: scipy; extra == "test"
Provides-Extra: dev
Requires-Dist: flake8; extra == "dev"
Requires-Dist: pytest; extra == "dev"
Requires-Dist: scipy; extra == "dev"
Requires-Dist: tox; extra == "dev"
Dynamic: license-file
